{
  "rainy_night": {
    "name": "🌧 雨夜",
    "text": "【雨夜色板】冷色调 6500K,主色深蓝紫 #2a3352,点缀粉紫霓虹 #d946ef + 青色霓虹 #06b6d4,湿润地面反光,雨丝斜飞。画面中等亮度,避免纯黑,细节清晰。",
    "keywords": [
      "雨夜",
      "雨中",
      "巷",
      "霓虹",
      "湿漉",
      "深夜雨",
      "暴雨"
    ]
  },
  "transition": {
    "name": "🌅 夜→晨过渡",
    "text": "【过渡色板】时间流转,色温从 #2a3352 深蓝 → #8b7db5 淡紫 → #ffc19b 浅橙 → #ffd89b 金。云层流动,雨丝渐停,城市轮廓在晨雾中浮现。柔和光影,8K,电影氛围。",
    "keywords": [
      "过渡",
      "夜转晨",
      "黎明",
      "天色渐明",
      "色温",
      "流转"
    ]
  },
  "dawn": {
    "name": "☀️ 清晨",
    "text": "【清晨色板】暖色 5000K,明亮通透。米白墙面 #f5efe0,原木色家具,窗光从画面右侧 45 度斜射而入,淡金晨雾,柔和温暖,8K,细节清晰。",
    "keywords": [
      "清晨",
      "早晨",
      "醒来",
      "起床",
      "晨光",
      "朝阳",
      "天亮"
    ]
  },
  "daylight": {
    "name": "🏙 白天",
    "text": "【白天色板】中性色温 6500K,天光均匀,明亮通透。冷暖平衡,阴影柔和。画面自然真实,8K,细节丰富。",
    "keywords": [
      "白天",
      "日间",
      "中午",
      "正午",
      "下午",
      "学校",
      "办公室"
    ]
  },
  "sunset": {
    "name": "🌇 黄昏",
    "text": "【黄昏色板】暖色 3500K,主色金橙 #ffa552 + 紫红 #9b5fb4,天空渐变紫金,长影子斜长。氛围浪漫,逆光剪影,8K。",
    "keywords": [
      "黄昏",
      "傍晚",
      "日落",
      "夕阳",
      "晚霞"
    ]
  },
  "night_indoor": {
    "name": "🕯 夜晚室内",
    "text": "【室内夜色板】暖灯 3200K,局部光源(台灯/吊灯/屏幕光),主色深棕 #2a1f18 + 暖黄 #ffb96b,阴影沉稳。画面有对比度,氛围温馨或压抑(视场景),8K。",
    "keywords": [
      "晚上",
      "深夜室内",
      "台灯",
      "卧室",
      "书房",
      "酒吧",
      "房间夜"
    ]
  }
}